odoo/addons/project_mail_chatter/README.rst
odoo/addons/project_mail_chatter/__init__.py
odoo/addons/project_mail_chatter/__manifest__.py
odoo/addons/project_mail_chatter/i18n/project_mail_chatter.pot
odoo/addons/project_mail_chatter/i18n/pt_BR.po
odoo/addons/project_mail_chatter/models/__init__.py
odoo/addons/project_mail_chatter/models/project.py
odoo/addons/project_mail_chatter/readme/CONTRIBUTORS.rst
odoo/addons/project_mail_chatter/readme/CREDITS.rst
odoo/addons/project_mail_chatter/readme/DESCRIPTION.rst
odoo/addons/project_mail_chatter/readme/ROADMAP.rst
odoo/addons/project_mail_chatter/static/description/icon.png
odoo/addons/project_mail_chatter/static/description/index.html
odoo/addons/project_mail_chatter/views/project_view.xml
odoo14_addon_project_mail_chatter-14.0.1.1.0.dist-info/METADATA
odoo14_addon_project_mail_chatter-14.0.1.1.0.dist-info/WHEEL
odoo14_addon_project_mail_chatter-14.0.1.1.0.dist-info/top_level.txt
odoo14_addon_project_mail_chatter-14.0.1.1.0.dist-info/RECORD
